{"like":0,"dislike":0,"links":[{"url":"http:\/\/www.utt.fr\/","number":3}],"formations":[{"name":"Universit\u00e9 de technologie de Troyes","forma":"Sciences fondamentales et applications","cursus":"1\u00e8re ann\u00e9e","effectif":"17","number":1},{"name":"Universit\u00e9 de Bourgogne","forma":"Langues","cursus":"2\u00e8me ann\u00e9e","effectif":"3","number":1},{"name":"Universit\u00e9 de Bourgogne","forma":"Droit, sciences politiques","cursus":"2\u00e8me ann\u00e9e","effectif":"15","number":1}]}